{
  "timestamp": "2021-07-21",
  "hostname": "epage-sc01",
  "os": "Linux",
  "os_ver": "4.4.0-19041-Microsoft",
  "arch": "x86_64",
  "cpus": "8",
  "libs": {
    "examples/argh-app/Cargo.toml": {
      "name": "argh",
      "manifest_path": "examples/argh-app/Cargo.toml",
      "crate": "argh",
      "version": "v0.1.5",
      "deps": 8,
      "build": {
        "results": [
          {
            "command": "cargo build --package argh-app",
            "mean": 12.9292520185,
            "stddev": 0.10485324479845598,
            "median": 12.9572348185,
            "user": 19.018437499999997,
            "system": 6.8599218749999995,
            "min": 12.7500726185,
            "max": 13.0039379185,
            "times": [
              12.7500726185,
              13.0039379185,
              12.9572348185,
              13.0034489185,
              12.931565818500001
            ]
          }
        ]
      },
      "size": 3304136
    },
    "examples/clap-app/Cargo.toml": {
      "name": "clap",
      "manifest_path": "examples/clap-app/Cargo.toml",
      "crate": "clap",
      "version": "v2.33.3",
      "deps": 8,
      "build": {
        "results": [
          {
            "command": "cargo build --package clap-app",
            "mean": 11.116230633999999,
            "stddev": 0.13168733398414575,
            "median": 11.154351153999999,
            "user": 18.699609375,
            "system": 6.116015625,
            "min": 10.961475254,
            "max": 11.249951653999998,
            "times": [
              11.154351153999999,
              10.993809253999999,
              11.221565854,
              11.249951653999998,
              10.961475254
            ]
          }
        ]
      },
      "size": 3915648
    },
    "examples/clap-minimal-app/Cargo.toml": {
      "name": "clap-minimal",
      "manifest_path": "examples/clap-minimal-app/Cargo.toml",
      "crate": "clap",
      "version": "v3.0.0-beta.2",
      "deps": 8,
      "build": {
        "results": [
          {
            "command": "cargo build --package clap-minimal-app",
            "mean": 11.148560703500001,
            "stddev": 0.1801362458281313,
            "median": 11.1903517435,
            "user": 17.890390625,
            "system": 6.205859375,
            "min": 10.886688643500001,
            "max": 11.3779441435,
            "times": [
              11.202273743500001,
              11.1903517435,
              11.0855452435,
              10.886688643500001,
              11.3779441435
            ]
          }
        ]
      },
      "size": 3813240
    },
    "examples/clap3-app/Cargo.toml": {
      "name": "clap3",
      "manifest_path": "examples/clap3-app/Cargo.toml",
      "crate": "clap",
      "version": "v3.0.0-beta.2",
      "deps": 23,
      "build": {
        "results": [
          {
            "command": "cargo build --package clap3-app",
            "mean": 26.6242260315,
            "stddev": 0.33845242308688417,
            "median": 26.5080386915,
            "user": 60.243359375,
            "system": 21.244296875,
            "min": 26.2071917915,
            "max": 27.0099533915,
            "times": [
              27.0099533915,
              26.4622611915,
              26.933685091500003,
              26.5080386915,
              26.2071917915
            ]
          }
        ]
      },
      "size": 3860880
    },
    "examples/clap_derive-app/Cargo.toml": {
      "name": "clap_derive",
      "manifest_path": "examples/clap_derive-app/Cargo.toml",
      "crate": "clap",
      "version": "v3.0.0-beta.2",
      "deps": 23,
      "build": {
        "results": [
          {
            "command": "cargo build --package clap_derive-app",
            "mean": 26.433862318000003,
            "stddev": 0.9975662195367049,
            "median": 26.918141478000003,
            "user": 59.4434375,
            "system": 20.913671875,
            "min": 24.669024278000002,
            "max": 27.024608578000002,
            "times": [
              26.918141478000003,
              26.927885978000003,
              27.024608578000002,
              26.629651278,
              24.669024278000002
            ]
          }
        ]
      },
      "size": 3861240
    },
    "examples/gumdrop-app/Cargo.toml": {
      "name": "gumdrop",
      "manifest_path": "examples/gumdrop-app/Cargo.toml",
      "crate": "gumdrop",
      "version": "v0.8.0",
      "deps": 5,
      "build": {
        "results": [
          {
            "command": "cargo build --package gumdrop-app",
            "mean": 10.716865883499999,
            "stddev": 0.14125723948084182,
            "median": 10.6656295435,
            "user": 14.015390625,
            "system": 4.8510937499999995,
            "min": 10.6030897435,
            "max": 10.953443843499999,
            "times": [
              10.6276307435,
              10.6656295435,
              10.7345355435,
              10.953443843499999,
              10.6030897435
            ]
          }
        ]
      },
      "size": 3298032
    },
    "examples/lexopt-app/Cargo.toml": {
      "name": "lexopt",
      "manifest_path": "examples/lexopt-app/Cargo.toml",
      "crate": "lexopt",
      "version": "v0.1.0",
      "deps": 0,
      "build": {
        "results": [
          {
            "command": "cargo build --package lexopt-app",
            "mean": 1.9656674545000001,
            "stddev": 0.016355955229304057,
            "median": 1.9571538145,
            "user": 1.1121875,
            "system": 0.9,
            "min": 1.9479225145,
            "max": 1.9832414145000001,
            "times": [
              1.9829741145,
              1.9570454145000002,
              1.9479225145,
              1.9832414145000001,
              1.9571538145
            ]
          }
        ]
      },
      "size": 3295768
    },
    "examples/null-app/Cargo.toml": {
      "name": "null",
      "manifest_path": "examples/null-app/Cargo.toml",
      "crate": null,
      "version": null,
      "deps": 0,
      "build": {
        "results": [
          {
            "command": "cargo build --package null-app",
            "mean": 1.1896718245,
            "stddev": 0.0512238153983379,
            "median": 1.1763250645,
            "user": 0.59328125,
            "system": 0.578828125,
            "min": 1.1311540645,
            "max": 1.2708507645,
            "times": [
              1.2708507645,
              1.1736204645000001,
              1.1311540645,
              1.1763250645,
              1.1964087645
            ]
          }
        ]
      },
      "size": 3258728
    },
    "examples/pico-args-app/Cargo.toml": {
      "name": "pico-args",
      "manifest_path": "examples/pico-args-app/Cargo.toml",
      "crate": "pico-args",
      "version": "v0.4.2",
      "deps": 0,
      "build": {
        "results": [
          {
            "command": "cargo build --package pico-args-app",
            "mean": 2.0220675530000003,
            "stddev": 0.06950518352088561,
            "median": 1.987720973,
            "user": 1.274609375,
            "system": 0.8565625000000001,
            "min": 1.951309973,
            "max": 2.113981273,
            "times": [
              1.9806917730000002,
              2.076633773,
              1.951309973,
              1.987720973,
              2.113981273
            ]
          }
        ]
      },
      "size": 3288360
    },
    "examples/structopt-app/Cargo.toml": {
      "name": "structopt",
      "manifest_path": "examples/structopt-app/Cargo.toml",
      "crate": "structopt",
      "version": "v0.3.22",
      "deps": 20,
      "build": {
        "results": [
          {
            "command": "cargo build --package structopt-app",
            "mean": 22.774286784,
            "stddev": 0.6735052822216114,
            "median": 22.530536344,
            "user": 60.908984375,
            "system": 19.0721875,
            "min": 22.046216644,
            "max": 23.693125544,
            "times": [
              23.236248044,
              22.365307344,
              22.046216644,
              22.530536344,
              23.693125544
            ]
          }
        ]
      },
      "size": 3916440
    },
    "examples/xflags-app/Cargo.toml": {
      "name": "xflags",
      "manifest_path": "examples/xflags-app/Cargo.toml",
      "crate": "xflags",
      "version": "v0.2.2",
      "deps": 3,
      "build": {
        "results": [
          {
            "command": "cargo build --package xflags-app",
            "mean": 6.435744421,
            "stddev": 0.09176711483145794,
            "median": 6.424678721,
            "user": 5.64328125,
            "system": 2.922265625,
            "min": 6.321503921,
            "max": 6.577244421,
            "times": [
              6.414266521,
              6.441028521,
              6.577244421,
              6.424678721,
              6.321503921
            ]
          }
        ]
      },
      "size": 3288872
    }
  }
}
